<?xml version="1.0" encoding="utf-8"?>
<resources name="ru" flag="ru" title="Russian">
	<string_add name="_bx_messenger_jump_to_the_bottom"><![CDATA[Перейти к последнему сообщению]]></string_add>
	<string_add name="_bx_messenger_mark_all_as_read"><![CDATA[Пометить все сообщения прочитанными]]></string_add>
	<string_add name="_bx_messenger_search_no_results"><![CDATA[Поиск ничего не нашёл]]></string_add>
	<string_add name="_bx_messenger_search_query_issue"><![CDATA[Появилась проблема при отправки запроса на сервер.]]></string_add>
	<string_add name="_bx_messenger_search_desc"><![CDATA[Присоединился - {1}<br/>Последний раз был - {0}]]></string_add>
</resources>